ss56/__init__.py
ss56/ss56.py
ss56-0.1.dist-info/LICENSE.txt
ss56-0.1.dist-info/METADATA
ss56-0.1.dist-info/WHEEL
ss56-0.1.dist-info/top_level.txt
ss56-0.1.dist-info/RECORD
