Metadata-Version: 2.1
Name: ss56
Version: 0.1
Summary: asdasdasda
Author: Yaromir Gusev
Author-email: yaromirarhideus@gmail.com
License: MIT
License-File: LICENSE.txt
Requires-Dist: pyperclip
